mplogger/__init__.py
mplogger/logger.py
mplogger/version.py
mplogger-1.1.0.dist-info/LICENSE
mplogger-1.1.0.dist-info/WHEEL
mplogger-1.1.0.dist-info/METADATA
mplogger-1.1.0.dist-info/RECORD
