Metadata-Version: 2.1
Name: mplogger
Version: 1.1.0
Summary: Multi-processing capable print-like logger for Python
Home-page: https://github.com/ELTE-DH/MPLogger
License: LGPLv3
Author: dlazesz
Requires-Python: >=3.8,<4.0
Classifier: Development Status :: 5 - Production/Stable
Classifier: License :: Other/Proprietary License
Classifier: Operating System :: OS Independent
Classifier: Programming Language :: Python :: 3
Classifier: Programming Language :: Python :: 3.10
Classifier: Programming Language :: Python :: 3.8
Classifier: Programming Language :: Python :: 3.9
Classifier: Topic :: Software Development :: Libraries :: Python Modules
Project-URL: Repository, https://github.com/ELTE-DH/MPLogger
